CHANGES.txt
DEPENDENCES.txt
README.txt
setup.py
src/ng/__init__.py
src/ng.utility.egg-info/PKG-INFO
src/ng.utility.egg-info/SOURCES.txt
src/ng.utility.egg-info/dependency_links.txt
src/ng.utility.egg-info/namespace_packages.txt
src/ng.utility.egg-info/not-zip-safe
src/ng.utility.egg-info/requires.txt
src/ng.utility.egg-info/top_level.txt
src/ng/utility/__init__.py
src/ng/utility/configure.zcml
src/ng/utility/ng.utility.txt
src/ng/utility/etc/ng.utility-configure.zcml
src/ng/utility/interfacewave/__init__.py
src/ng/utility/interfacewave/configure.zcml
src/ng/utility/interfacewave/interfaces.py
src/ng/utility/interfacewave/interfacewave.py
src/ng/utility/intidsvocabulary/__init__.py
src/ng/utility/intidsvocabulary/configure.zcml
src/ng/utility/intidsvocabulary/intidsvocabulary.py
src/ng/utility/intidsvocabulary/etc/intidsvocabulary-configure.zcml
src/ng/utility/intidsvocabulary/etc/ng.utility.intidsvocabulary-configure.zcml
src/ng/utility/objecteventchannel/__init__.py
src/ng/utility/objecteventchannel/configure.zcml
src/ng/utility/objecteventchannel/objecteventchannel.py
src/ng/utility/objecteventchannel/objecteventchannel.txt
src/ng/utility/objecteventchannel/etc/ng.utility.objecteventchannel-configure.zcml
