Metadata-Version: 1.0
Name: ng.utility
Version: 1.0.3
Summary: Collection of small but useful utilities and other stuff
Home-page: http://www.dreambot.ru/product/DreamBotZope3Releases/ng.utility
Author: Andrey Orlov
Author-email: cray@neural.ru
License: GPL v2.1
Platform: UNKNOWN
Classifier: Environment :: Web Environment
Classifier: Intended Audience :: Developers
Classifier: License :: OSI Approved :: GNU General Public License (GPL)
Classifier: Programming Language :: Python
Classifier: Operating System :: OS Independent
Classifier: Topic :: Internet :: WWW/HTTP
Classifier: Framework :: Zope3
